nonebot_plugin_antimonkey/__init__.py
nonebot_plugin_antimonkey/malou.py
nonebot_plugin_antimonkey/monkey_test.jpg
nonebot_plugin_antimonkey-1.1.1.dist-info/entry_points.txt
nonebot_plugin_antimonkey-1.1.1.dist-info/LICENSE
nonebot_plugin_antimonkey-1.1.1.dist-info/METADATA
nonebot_plugin_antimonkey-1.1.1.dist-info/WHEEL
nonebot_plugin_antimonkey-1.1.1.dist-info/RECORD
