Metadata-Version: 2.1
Name: nonebot-plugin-antimonkey
Version: 1.1.1
Summary: 一个用于自动检测和撤回包含猴子图片的QQ机器人插件。
Home-page: https://github.com/phquathi/nonebot_plugin_antimonkey
Keywords: nonebot,plugin,antimonkey
Author: phquathi
Author-email: yangziqi233@gmail.com
Requires-Python: >=3.7,<4.0
Classifier: Programming Language :: Python :: 3
Classifier: Programming Language :: Python :: 3.7
Classifier: Programming Language :: Python :: 3.8
Classifier: Programming Language :: Python :: 3.9
Classifier: Programming Language :: Python :: 3.10
Classifier: Programming Language :: Python :: 3.11
Classifier: Programming Language :: Python :: 3.12
Requires-Dist: aiohttp (>=3.7.4,<4.0.0)
Requires-Dist: keras (>=2.4.3,<3.0.0)
Requires-Dist: nonebot-adapter-onebot (>=2.0.0,<3.0.0)
Requires-Dist: nonebot-plugin-apscheduler (>=0.4.0,<0.5.0)
Requires-Dist: nonebot2 (>=2.0.0,<3.0.0)
Requires-Dist: numpy (>=1.19.5,<2.0.0)
Requires-Dist: opencv-python (>=4.5.1.48,<5.0.0.0)
Requires-Dist: tensorflow (>=2.4.1,<3.0.0)
Project-URL: Repository, https://github.com/phquathi/nonebot_plugin_antimonkey
